LICENSE
MANIFEST.in
README.rst
requirements.txt
setup.py
django_pages_cms_extensions.egg-info/PKG-INFO
django_pages_cms_extensions.egg-info/SOURCES.txt
django_pages_cms_extensions.egg-info/dependency_links.txt
django_pages_cms_extensions.egg-info/not-zip-safe
django_pages_cms_extensions.egg-info/requires.txt
django_pages_cms_extensions.egg-info/top_level.txt
docs/FIXME
docs/TODO
docs/installation.rst
docs/usage.rst
docs/example_app/manage.py
docs/example_app/requirements.txt
docs/example_app/example_app/__init__.py
docs/example_app/example_app/settings.py
docs/example_app/example_app/urls.py
docs/example_app/example_app/wsgi.py
docs/example_app/templates/pages/pages/page.html
pagesext/__init__.py
pagesext/conf.py
pagesext/storage.py
pagesext/admin/__init__.py
pagesext/admin/pagefilecontent.py
pagesext/admin/pageimagecontent.py
pagesext/admin/pagetagscontent.py
pagesext/admin/pagevideocontent.py
pagesext/fixtures/ext_content_types.yaml
pagesext/migrations/0001_initial.py
pagesext/migrations/__init__.py
pagesext/models/__init__.py
pagesext/models/pagefilecontent.py
pagesext/models/pageimagecontent.py
pagesext/models/pagetagscontent.py
pagesext/models/pagevideocontent.py
pagesext/templatetags/__init__.py
pagesext/templatetags/pagesext_tags.py
pagesext/tests/__init__.py
pagesext/tests/base.py
pagesext/tests/runtests.py
pagesext/tests/test_pages.py
pagesext/tests/test_settings.py
pagesext/tests/urls.py